<xml xmlns="http://www.w3.org/1999/xhtml">
  <tab name="init" type="InitTab" active="false" scrollx="-4.999999999999773" scrolly="306.9999999999999" scale="1">
    <block xmlns="https://developers.google.com/blockly/xml" type="initSettings" id="pMCwPp2^zhNEz?!U+j1#" x="210" y="-210">
      <field name="LOAD_COMP_ASSETS">FALSE</field>
      <field name="FULLSCREEN">FALSE</field>
      <field name="BKG_TRANSPARENCY">TRUE</field>
      <field name="PRESERVE_DRAW_BUF">FALSE</field>
      <field name="FADE_ANNOTATIONS">TRUE</field>
    </block>
  </tab>
  <tab name="main" type="MainTab" active="true" scrollx="903.2857666015625" scrolly="572.9670715332031" scale="0.7655186873167403">
    <variables xmlns="https://developers.google.com/blockly/xml">
      <variable id="MfT|5S8#?b5N]r-q:a*c" type="">screen_fade_color_2</variable>
      <variable id="_Ji;N`-6.dO#5qZ-]/Az" type="">cubeClicked</variable>
      <variable id="7*^UsO?.7AAZk=eZju5]" type="">offset var</variable>
    </variables>
    <block xmlns="https://developers.google.com/blockly/xml" type="procedures_defnoreturn" id="tP%WbG(]DzyuXA~M]F{4" disabled="true" x="-590" y="-550">
      <field name="NAME">SET_TEXT</field>
      <comment pinned="false" h="80" w="160">Describe this function...</comment>
      <statement name="STACK">
        <block type="addHTMLElement" id="deyfpttnsDq$flN0LB`n">
          <field name="ELEMENT">div</field>
          <field name="MODE">TO</field>
          <field name="PARENT">TRUE</field>
          <value name="ID">
            <shadow type="text" id=":@[RKAtR`3hww=Cm5SJW">
              <field name="TEXT">text</field>
            </shadow>
          </value>
          <value name="TARGET_ID">
            <shadow type="DOMObjectSelector" id="hCd{X|jS};V?)k(_bIuf">
              <field name="DOM_OBJECT">CONTAINER</field>
            </shadow>
          </value>
          <next>
            <block type="setHTMLElemStyle" id="4bgq1m~~G|QXIk-cnf1P">
              <field name="PROPERTY">display</field>
              <field name="PARENT">FALSE</field>
              <value name="VALUE">
                <block type="text" id="^}2._UmL84TQdH(3I,(N">
                  <field name="TEXT">block</field>
                </block>
              </value>
              <value name="ID">
                <shadow type="text" id="1f!^krG]a3Q(Wt)n=?ru">
                  <field name="TEXT">text</field>
                </shadow>
              </value>
              <next>
                <block type="setHTMLElemStyle" id="(]V3k=;d$R72-2:V({@r">
                  <field name="PROPERTY">left</field>
                  <field name="PARENT">FALSE</field>
                  <value name="VALUE">
                    <block type="text" id="]q,=*IZY5Z#ouz[5qVNV">
                      <field name="TEXT">10px</field>
                    </block>
                  </value>
                  <value name="ID">
                    <shadow type="text" id="Z?Ogh-~Vu*+pINV,Ij*~">
                      <field name="TEXT">text</field>
                    </shadow>
                  </value>
                  <next>
                    <block type="setHTMLElemStyle" id=")/K8Oxim4/N6y_4(;M?d">
                      <field name="PROPERTY">top</field>
                      <field name="PARENT">FALSE</field>
                      <value name="VALUE">
                        <block type="text" id="tlMmXE%:l]2UJt9wUuhl">
                          <field name="TEXT">10px</field>
                        </block>
                      </value>
                      <value name="ID">
                        <shadow type="text" id="K08P_X{b#;;%}3Ur[Hd4">
                          <field name="TEXT">text</field>
                        </shadow>
                      </value>
                      <next>
                        <block type="setHTMLElemStyle" id="P6`ugI~za31b=QgI?TTg">
                          <field name="PROPERTY">zIndex</field>
                          <field name="PARENT">FALSE</field>
                          <value name="VALUE">
                            <block type="text" id="F^UAgxmm%zQ:5kSZV[5*">
                              <field name="TEXT">200</field>
                            </block>
                          </value>
                          <value name="ID">
                            <shadow type="text" id="e0h^w?5$~+v1hg+}S*w0">
                              <field name="TEXT">text</field>
                            </shadow>
                          </value>
                          <next>
                            <block type="setHTMLElemStyle" id="c-tFh_GCO[5jO9qd)JuA">
                              <field name="PROPERTY">color</field>
                              <field name="PARENT">FALSE</field>
                              <value name="VALUE">
                                <block type="text" id="F:X,}6!]~Vx$PKcQ+`x3">
                                  <field name="TEXT">cyan</field>
                                </block>
                              </value>
                              <value name="ID">
                                <shadow type="text" id="11nE,;ueloCpVTNqaM1U">
                                  <field name="TEXT">text</field>
                                </shadow>
                              </value>
                              <next>
                                <block type="setHTMLElemStyle" id="c-#%?v+IZYmQsce2VMye">
                                  <field name="PROPERTY">fontFamily</field>
                                  <field name="PARENT">FALSE</field>
                                  <value name="VALUE">
                                    <block type="text" id="@4B)_^jR@uGgYSi8OhM{">
                                      <field name="TEXT">Arial</field>
                                    </block>
                                  </value>
                                  <value name="ID">
                                    <shadow type="text" id="@*Ep`f[byx$h.YwnBZg!">
                                      <field name="TEXT">text</field>
                                    </shadow>
                                  </value>
                                  <next>
                                    <block type="setHTMLElemStyle" id="`xC8XS;3oroVi,$OZe^y">
                                      <field name="PROPERTY">fontSize</field>
                                      <field name="PARENT">FALSE</field>
                                      <value name="VALUE">
                                        <block type="text" id="Wwj9qVS,4D|d:u,Kb+/2">
                                          <field name="TEXT">30</field>
                                        </block>
                                      </value>
                                      <value name="ID">
                                        <shadow type="text" id="Zs9Bf5Bq.`HdJC%KC=6K">
                                          <field name="TEXT">text</field>
                                        </shadow>
                                      </value>
                                      <next>
                                        <block type="setHTMLElemAttribute" id="KUNm$/]0q@[DKc7OLL,H">
                                          <field name="ATTRIBUTE">innerHTML</field>
                                          <field name="PARENT">FALSE</field>
                                          <value name="VALUE">
                                            <block type="text" id="k{GU%R7Lg4L60n+GUi4)">
                                              <field name="TEXT">LINEAR GRADIENT</field>
                                            </block>
                                          </value>
                                          <value name="ID">
                                            <shadow type="text" id="Ujv)=yf5Q8qOyg*+V,ZT">
                                              <field name="TEXT">text</field>
                                            </shadow>
                                          </value>
                                        </block>
                                      </next>
                                    </block>
                                  </next>
                                </block>
                              </next>
                            </block>
                          </next>
                        </block>
                      </next>
                    </block>
                  </next>
                </block>
              </next>
            </block>
          </next>
        </block>
      </statement>
    </block>
    <block xmlns="https://developers.google.com/blockly/xml" type="procedures_callnoreturn" id="@w4L|kr(8z,eC$|d;Nr@" x="-1010" y="-370">
      <mutation name="MAIN"/>
    </block>
    <block xmlns="https://developers.google.com/blockly/xml" type="procedures_defnoreturn" id="|Stve.guQwe)?7UnX]H3" x="-1010" y="-290">
      <field name="NAME">MAIN</field>
      <comment pinned="false" h="80" w="160">Describe this function...</comment>
      <statement name="STACK">
        <block type="procedures_callnoreturn" id="DVMpk87~AGRgUHNdoD%,">
          <mutation name="GRADIENT_BACKGROUND_TEAL"/>
          <next>
            <block type="procedures_callnoreturn" id="@=y`kX2~!%Nv]_qS*q!Y" disabled="true">
              <mutation name="SET_TEXT"/>
              <next>
                <block type="procedures_callnoreturn" id="nImT*!cwSFyyK/OdSt[%">
                  <mutation name="FADE_FROM_BLACK"/>
                  <next>
                    <block type="variables_set" id=";Xn5S52Bk?QDRN5OThJu">
                      <field name="VAR" id="_Ji;N`-6.dO#5qZ-]/Az">cubeClicked</field>
                      <value name="VALUE">
                        <block type="math_number" id=":S^UBLow2xh]G@jy(L1I">
                          <field name="NUM">0</field>
                        </block>
                      </value>
                    </block>
                  </next>
                </block>
              </next>
            </block>
          </next>
        </block>
      </statement>
    </block>
    <block xmlns="https://developers.google.com/blockly/xml" type="procedures_defnoreturn" id=",EVX)M);4/#h=;=|r^pN" x="-1430" y="-50">
      <field name="NAME">GRADIENT_BACKGROUND_CENTER</field>
      <comment pinned="false" h="80" w="160">Describe this function...</comment>
      <statement name="STACK">
        <block type="GLIFTEK_v3d_Plugins_Backgrounds/GLIFTEK_BACKGROUNDS_Generate_Gradient_Background" id="#zDa^femkQ~}TemBMlp0">
          <field name="typeDropdown">gradientRadial</field>
          <field name="colorInput_1_PICKER">#ffff99</field>
          <field name="color2Checkbox">FALSE</field>
          <field name="colorInput_2_PICKER">#b87132</field>
          <field name="colorInput_3_PICKER">#cc6600</field>
          <value name="colorInput_1_TEXT">
            <shadow type="text" id="z!t~m_WORA?tkY?H/zA=">
              <field name="TEXT"/>
            </shadow>
          </value>
          <value name="colorInput_1_OFFSET">
            <shadow type="math_number" id="7hDN~;6|RYv02d[}Y}d2">
              <field name="NUM">0.5</field>
            </shadow>
          </value>
          <value name="colorInput_2_TEXT">
            <shadow type="text" id="oxtYR^fKKb5v|Du9?TU#">
              <field name="TEXT"/>
            </shadow>
          </value>
          <value name="colorInput_2_OFFSET">
            <shadow type="math_number" id="$$5e?H%,)uaDvid[Afu|">
              <field name="NUM">0.6</field>
            </shadow>
          </value>
          <value name="colorInput_3_TEXT">
            <shadow type="text" id="eqepg}n{nq`8%6E(qn[V">
              <field name="TEXT"/>
            </shadow>
          </value>
          <value name="colorInput_3_OFFSET">
            <shadow type="math_number" id="6+4@v0n!IK!`)*;zGga,">
              <field name="NUM">1</field>
            </shadow>
          </value>
        </block>
      </statement>
    </block>
    <block xmlns="https://developers.google.com/blockly/xml" type="procedures_defnoreturn" id="shDf_GtIhrJ=LjE^caYS" x="50" y="-110">
      <field name="NAME">CLICK_CUBE</field>
      <comment pinned="false" h="80" w="160">Describe this function...</comment>
      <statement name="STACK">
        <block type="whenClicked" id="fvEh}_~q~Rb?`sHOVDNG">
          <mutation xmlns="http://www.w3.org/1999/xhtml" adveventoptions="false" enableifmissed="false"></mutation>
          <field name="X_RAY">FALSE</field>
          <field name="DOUBLE_CLICK">FALSE</field>
          <field name="LEFT_BUTTON">TRUE</field>
          <field name="MIDDLE_BUTTON">TRUE</field>
          <field name="RIGHT_BUTTON">TRUE</field>
          <value name="VALUE">
            <shadow type="objectList" id="e.y0I#|deHb@MlQ/_Yo.">
              <field name="FIELDNAME">Cube</field>
            </shadow>
          </value>
          <statement name="DO">
            <block type="procedures_callnoreturn" id="KgT]eX@ykVe*E7?5x}%t">
              <mutation name="FADE_IN_OUT"/>
            </block>
          </statement>
        </block>
      </statement>
    </block>
    <block xmlns="https://developers.google.com/blockly/xml" type="procedures_defnoreturn" id="#nHwxLy_A}tOExRd~%%h" x="-1010" y="-50">
      <field name="NAME">GRADIENT_BACKGROUND_TEAL</field>
      <comment pinned="false" h="80" w="160">Describe this function...</comment>
      <statement name="STACK">
        <block type="GLIFTEK_v3d_Plugins_Backgrounds/GLIFTEK_BACKGROUNDS_Generate_Gradient_Background" id="u~1PK*^Cjn-Qrr10L|]D">
          <field name="typeDropdown">gradientLinear</field>
          <field name="colorInput_1_PICKER">#000000</field>
          <field name="color2Checkbox">FALSE</field>
          <field name="colorInput_2_PICKER">#b87132</field>
          <field name="colorInput_3_PICKER">#33ffff</field>
          <value name="colorInput_1_TEXT">
            <shadow type="text" id="dPwAVg))J4OE`W2}[Naq">
              <field name="TEXT">TEAL</field>
            </shadow>
          </value>
          <value name="colorInput_1_OFFSET">
            <shadow type="math_number" id="D]|[B=xB=KIk~Wj.!*?Y">
              <field name="NUM">0.5</field>
            </shadow>
          </value>
          <value name="colorInput_2_TEXT">
            <shadow type="text" id="4yC!lPIR2gP_p%mR#QnC">
              <field name="TEXT"/>
            </shadow>
          </value>
          <value name="colorInput_2_OFFSET">
            <shadow type="math_number" id="^%^i2U?Su5ZWC_yumpb6">
              <field name="NUM">0.2</field>
            </shadow>
          </value>
          <value name="colorInput_3_TEXT">
            <shadow type="text" id=")r,6hQ@7J{Mba~,!?4%H">
              <field name="TEXT"/>
            </shadow>
          </value>
          <value name="colorInput_3_OFFSET">
            <shadow type="math_number" id="Q.uE}xfqv74*${Ywb-XK">
              <field name="NUM">1</field>
            </shadow>
          </value>
        </block>
      </statement>
    </block>
    <block xmlns="https://developers.google.com/blockly/xml" type="procedures_defnoreturn" id="KvS4-:QvpF*@.Ad,1m)x" x="-590" y="-50">
      <field name="NAME">FADE_FROM_BLACK</field>
      <comment pinned="false" h="80" w="160">Describe this function...</comment>
      <statement name="STACK">
        <block type="variables_set" id="hV7I/)9+-Mt~{_z%KU9S">
          <field name="VAR" id="MfT|5S8#?b5N]r-q:a*c">screen_fade_color_2</field>
          <value name="VALUE">
            <block type="text" id="5@t{{W97Re;!B7lgSX9I">
              <field name="TEXT">#31626b</field>
            </block>
          </value>
          <next>
            <block type="comment" id="%kf^|,xOTlIqp~EFI{BD">
              <field name="TEXT">fade FROM black</field>
              <next>
                <block type="GLIFTEK_v3d_Plugins_Backgrounds/GLIFTEK_BACKGROUNDS_Screen_Fade" id="@RUoe!j;v8/Fot=b?k1J">
                  <field name="typeDropdown">out</field>
                  <field name="colorInput_1_PICKER">#000000</field>
                  <field name="delete_When_Done_Checkbox">TRUE</field>
                  <value name="screenFade_ID_Input">
                    <shadow type="text" id=";6a0c5I/RZzrq:ww$9?q">
                      <field name="TEXT">screenFade_1</field>
                    </shadow>
                  </value>
                  <value name="screenFade_Z_Index_Input">
                    <shadow type="math_number" id="w/Dp)_1o{*_~8aj+)Bm2">
                      <field name="NUM">20</field>
                    </shadow>
                  </value>
                  <value name="screenFade_Pause_Input">
                    <block type="math_number" id="BM1z8,s|$=?,Ag-LH[T5">
                      <field name="NUM">2</field>
                    </block>
                  </value>
                  <value name="screenFade_Duration_Input">
                    <shadow type="math_number" id=")#1upNT#np0]M.:;frP;">
                      <field name="NUM">1</field>
                    </shadow>
                  </value>
                  <value name="colorInput_1_TEXT">
                    <shadow type="text" id="S1S3ZMLn;BBSSP0nyG86">
                      <field name="TEXT"/>
                    </shadow>
                  </value>
                  <statement name="whenDone_Statement_Input">
                    <block type="procedures_callnoreturn" id="QU(zy?H8eeQ[WV~TTjjA">
                      <mutation name="CLICK_CUBE"/>
                    </block>
                  </statement>
                  <next>
                    <block type="variables_set" id=":_=mrKDdYMb2|3%6l+[O">
                      <field name="VAR" id="7*^UsO?.7AAZk=eZju5]">offset var</field>
                      <value name="VALUE">
                        <block type="math_number" id="HlR0Q@*@9#MUaZ_rlyir">
                          <field name="NUM">0</field>
                        </block>
                      </value>
                    </block>
                  </next>
                </block>
              </next>
            </block>
          </next>
        </block>
      </statement>
    </block>
    <block xmlns="https://developers.google.com/blockly/xml" type="procedures_defnoreturn" id="#QyU5cEOS)Z#x9%vK_7f" x="50" y="110">
      <field name="NAME">FADE_IN_OUT</field>
      <comment pinned="false" h="80" w="160">Describe this function...</comment>
      <statement name="STACK">
        <block type="controls_if" id="X*+s2#KtcQEzz?pKnCm;">
          <mutation elseif="1"/>
          <value name="IF0">
            <block type="logic_compare" id="mK0=6WgEzhAhiMTcx{|`">
              <field name="OP">EQ</field>
              <value name="A">
                <block type="variables_get" id="6bTVhXPtcPw/1)yMPC$K">
                  <field name="VAR" id="_Ji;N`-6.dO#5qZ-]/Az">cubeClicked</field>
                </block>
              </value>
              <value name="B">
                <block type="math_number" id="Sm}EW]X1h7/I)Bv8c.s/">
                  <field name="NUM">0</field>
                </block>
              </value>
            </block>
          </value>
          <statement name="DO0">
            <block type="comment" id="(gRcOuKT~tFf,ypcu+-c">
              <field name="TEXT">fade TO teal</field>
              <next>
                <block type="GLIFTEK_v3d_Plugins_Backgrounds/GLIFTEK_BACKGROUNDS_Screen_Fade" id="0AT)%pNTwX+]8Ov$@~{v">
                  <field name="typeDropdown">in</field>
                  <field name="colorInput_1_PICKER">#cc0000</field>
                  <field name="delete_When_Done_Checkbox">TRUE</field>
                  <value name="screenFade_ID_Input">
                    <shadow type="text" id=":Fe,{XG:E,SPbu8#|.M)">
                      <field name="TEXT">screenFade_2</field>
                    </shadow>
                  </value>
                  <value name="screenFade_Z_Index_Input">
                    <shadow type="math_number" id="ug$RoF./{HxrM,+74Ws!">
                      <field name="NUM">20</field>
                    </shadow>
                  </value>
                  <value name="screenFade_Pause_Input">
                    <block type="math_number" id="aU?wgSO2*(VE9V5M[)k$">
                      <field name="NUM">0</field>
                    </block>
                  </value>
                  <value name="screenFade_Duration_Input">
                    <shadow type="math_number" id="E1VN6*(4Iw#lfOX)Yw)[">
                      <field name="NUM">0.5</field>
                    </shadow>
                  </value>
                  <value name="colorInput_1_TEXT">
                    <shadow type="text" id="{?:ELkwR6y{?EI54Ma39">
                      <field name="TEXT">black</field>
                    </shadow>
                  </value>
                  <statement name="whenDone_Statement_Input">
                    <block type="procedures_callnoreturn" id="61uRqUJ..nt4zqzd)CnM">
                      <mutation name="SCREEN_VIGNETTE"/>
                      <next>
                        <block type="GLIFTEK_v3d_Plugins_Backgrounds/GLIFTEK_BACKGROUNDS_Set_Background_Image" id="7m`[jt=cNI48lKOu48St">
                          <value name="imageURLInput">
                            <shadow type="text" id="os$-=]/SD-*!gc[!1YyY">
                              <field name="TEXT">./bg_clouds_godrays_01.jpg</field>
                            </shadow>
                          </value>
                          <next>
                            <block type="setHTMLElemAttribute" id="Yyzj($p+z6p,KPj`,2N!" disabled="true">
                              <field name="ATTRIBUTE">innerHTML</field>
                              <field name="PARENT">FALSE</field>
                              <value name="VALUE">
                                <block type="text" id="(~{d:|%H*AQy93xx=8!~">
                                  <field name="TEXT">BACKGROUND IMAGE</field>
                                </block>
                              </value>
                              <value name="ID">
                                <shadow type="text" id="J2P8EbM8)f!Cy#3)[d3p">
                                  <field name="TEXT">text</field>
                                </shadow>
                              </value>
                              <next>
                                <block type="comment" id="7,v*AUBH_OtiQ[Z/nxKQ">
                                  <field name="TEXT">TIMER OVERLAPS FADE PAUSE</field>
                                  <next>
                                    <block type="setTimeout" id="R?G=eB^WhQL2AfvypDk)">
                                      <value name="VALUE">
                                        <shadow type="math_number" id="3fPNj2D;#5zhU0oo+N:|">
                                          <field name="NUM">0.25</field>
                                        </shadow>
                                      </value>
                                      <statement name="DO">
                                        <block type="removeHTMLElement" id="JZ}-2mz7h=d$b?^qE4X=">
                                          <field name="PARENT">FALSE</field>
                                          <value name="ID">
                                            <shadow type="text" id="jN-N3%byBEHlfX#Bwojh">
                                              <field name="TEXT">screenFade_2</field>
                                            </shadow>
                                          </value>
                                        </block>
                                      </statement>
                                      <next>
                                        <block type="GLIFTEK_v3d_Plugins_Backgrounds/GLIFTEK_BACKGROUNDS_Screen_Fade" id="EQp(kFnH-k-VOs}6^)4;">
                                          <field name="typeDropdown">out</field>
                                          <field name="colorInput_1_PICKER">#cc0000</field>
                                          <field name="delete_When_Done_Checkbox">TRUE</field>
                                          <value name="screenFade_ID_Input">
                                            <shadow type="text" id="*%KDjHR:qS*^%Fu7zbrC">
                                              <field name="TEXT">screenFade_3</field>
                                            </shadow>
                                          </value>
                                          <value name="screenFade_Z_Index_Input">
                                            <shadow type="math_number" id="F0l#_!%MLHubB*2/YFp@">
                                              <field name="NUM">5</field>
                                            </shadow>
                                          </value>
                                          <value name="screenFade_Pause_Input">
                                            <block type="math_number" id="N)l]uNo:;XqYlu7mnY0v">
                                              <field name="NUM">0.5</field>
                                            </block>
                                          </value>
                                          <value name="screenFade_Duration_Input">
                                            <shadow type="math_number" id="%;NIFEy{BRB0JIN`{:[(">
                                              <field name="NUM">0.5</field>
                                            </shadow>
                                          </value>
                                          <value name="colorInput_1_TEXT">
                                            <shadow type="text" id="}$0U]bfagXl1F.aPvy2r">
                                              <field name="TEXT">black</field>
                                            </shadow>
                                          </value>
                                          <statement name="whenDone_Statement_Input">
                                            <block type="variables_set" id="0|U+-s8f=-xB)A/?Sb1T">
                                              <field name="VAR" id="_Ji;N`-6.dO#5qZ-]/Az">cubeClicked</field>
                                              <value name="VALUE">
                                                <block type="math_number" id="tZ6E#cD%T.WWIP:tubpf">
                                                  <field name="NUM">1</field>
                                                </block>
                                              </value>
                                              <next>
                                                <block type="procedures_callnoreturn" id="5?SlPaFVW{{ET@S`0VXK">
                                                  <mutation name="CLICK_CUBE"/>
                                                </block>
                                              </next>
                                            </block>
                                          </statement>
                                        </block>
                                      </next>
                                    </block>
                                  </next>
                                </block>
                              </next>
                            </block>
                          </next>
                        </block>
                      </next>
                    </block>
                  </statement>
                </block>
              </next>
            </block>
          </statement>
          <value name="IF1">
            <block type="logic_compare" id="/SmBX[R47ZkvG]p4JR2$">
              <field name="OP">EQ</field>
              <value name="A">
                <block type="variables_get" id="dC6UBPu1Xbm_$]zIj4w9">
                  <field name="VAR" id="_Ji;N`-6.dO#5qZ-]/Az">cubeClicked</field>
                </block>
              </value>
              <value name="B">
                <block type="math_number" id=":Gjze-gqs#rHN^G^2=rU">
                  <field name="NUM">1</field>
                </block>
              </value>
            </block>
          </value>
          <statement name="DO1">
            <block type="GLIFTEK_v3d_Plugins_Backgrounds/GLIFTEK_BACKGROUNDS_Screen_Fade" id="Wc;g$-S2i9QWu^76VkNI">
              <field name="typeDropdown">in</field>
              <field name="colorInput_1_PICKER">#cc0000</field>
              <field name="delete_When_Done_Checkbox">TRUE</field>
              <value name="screenFade_ID_Input">
                <shadow type="text" id="VG:$nc4=Qd#}POiCYi~+">
                  <field name="TEXT">screenFade_4</field>
                </shadow>
              </value>
              <value name="screenFade_Z_Index_Input">
                <shadow type="math_number" id="cbQN.cy7RBv*$tpOxLO_">
                  <field name="NUM">20</field>
                </shadow>
              </value>
              <value name="screenFade_Pause_Input">
                <block type="math_number" id="J:SC~i[Q4JLa/8J#/*@[">
                  <field name="NUM">0</field>
                </block>
              </value>
              <value name="screenFade_Duration_Input">
                <shadow type="math_number" id="64)B~!-61hh[8F,IH*mk">
                  <field name="NUM">0.5</field>
                </shadow>
              </value>
              <value name="colorInput_1_TEXT">
                <shadow type="text" id="MzlWvDs84+NvY|n1EA1q">
                  <field name="TEXT">black</field>
                </shadow>
              </value>
              <statement name="whenDone_Statement_Input">
                <block type="procedures_callnoreturn" id="~H.b3IbQY+`=oDEegxw6">
                  <mutation name="GRADIENT_BACKGROUND_CENTER"/>
                  <next>
                    <block type="setHTMLElemAttribute" id="]5/#HGs^__;39-%V92hg" disabled="true">
                      <field name="ATTRIBUTE">innerHTML</field>
                      <field name="PARENT">FALSE</field>
                      <value name="VALUE">
                        <block type="text" id="J6%7kT_#ri@%B;rxVH7T">
                          <field name="TEXT">RADIAL GRADIENT</field>
                        </block>
                      </value>
                      <value name="ID">
                        <shadow type="text" id="bmzGZ,-Z|=!T4B^PY1xM">
                          <field name="TEXT">text</field>
                        </shadow>
                      </value>
                      <next>
                        <block type="comment" id="J4OCtfsb4IB`,##2/PFX">
                          <field name="TEXT">TIMER OVERLAPS FADE PAUSE</field>
                          <next>
                            <block type="setTimeout" id="anh%lF-k[|]$W?.y42pw">
                              <value name="VALUE">
                                <shadow type="math_number" id="49$m=a?c_.Bn~Xc*+`o$">
                                  <field name="NUM">0.25</field>
                                </shadow>
                              </value>
                              <statement name="DO">
                                <block type="removeHTMLElement" id="+:8|5PUO1~((wH?;u36@">
                                  <field name="PARENT">FALSE</field>
                                  <value name="ID">
                                    <shadow type="text" id="Lyni:ANXP+g8S!0kBc#@">
                                      <field name="TEXT">screenFade_4</field>
                                    </shadow>
                                  </value>
                                </block>
                              </statement>
                              <next>
                                <block type="GLIFTEK_v3d_Plugins_Backgrounds/GLIFTEK_BACKGROUNDS_Screen_Fade" id="29@@0Q7?{mc:|09gQ2$S">
                                  <field name="typeDropdown">out</field>
                                  <field name="colorInput_1_PICKER">#cc0000</field>
                                  <field name="delete_When_Done_Checkbox">TRUE</field>
                                  <value name="screenFade_ID_Input">
                                    <shadow type="text" id="o-|xA=]+fmO22BxFuVjb">
                                      <field name="TEXT">screenFade_5</field>
                                    </shadow>
                                  </value>
                                  <value name="screenFade_Z_Index_Input">
                                    <shadow type="math_number" id="74bZE1gYfX;Qx]Cn:Fuh">
                                      <field name="NUM">5</field>
                                    </shadow>
                                  </value>
                                  <value name="screenFade_Pause_Input">
                                    <block type="math_number" id="|3G{:[#UzV0s7H6EIBs#">
                                      <field name="NUM">0.5</field>
                                    </block>
                                  </value>
                                  <value name="screenFade_Duration_Input">
                                    <shadow type="math_number" id="4{#..h`,wstH{qk=1wwt">
                                      <field name="NUM">0.5</field>
                                    </shadow>
                                  </value>
                                  <value name="colorInput_1_TEXT">
                                    <shadow type="text" id="eea5JsJPt?grcmF/Z2|9">
                                      <field name="TEXT">black</field>
                                    </shadow>
                                  </value>
                                  <statement name="whenDone_Statement_Input">
                                    <block type="variables_set" id="D83)?6xp@0JAwpSA-C!S">
                                      <field name="VAR" id="_Ji;N`-6.dO#5qZ-]/Az">cubeClicked</field>
                                      <value name="VALUE">
                                        <block type="math_number" id="!=.ze^]|7%~/T#f74F$C">
                                          <field name="NUM">2</field>
                                        </block>
                                      </value>
                                      <next>
                                        <block type="procedures_callnoreturn" id="mMkUjja@lFuHCP^I1r(R">
                                          <mutation name="CLICK_CUBE"/>
                                        </block>
                                      </next>
                                    </block>
                                  </statement>
                                </block>
                              </next>
                            </block>
                          </next>
                        </block>
                      </next>
                    </block>
                  </next>
                </block>
              </statement>
            </block>
          </statement>
        </block>
      </statement>
    </block>
    <block xmlns="https://developers.google.com/blockly/xml" type="procedures_defnoreturn" id="}!lmtLIT2f+;#)Crjk/_" x="-1010" y="710">
      <field name="NAME">SCREEN_VIGNETTE</field>
      <comment pinned="false" h="80" w="160">Describe this function...</comment>
      <statement name="STACK">
        <block type="GLIFTEK_v3d_Plugins_Backgrounds/GLIFTEK_BACKGROUNDS_Screen_Vignette" id="fHI@~jZECr}/b5c8-=-g">
          <value name="screenVignette_ID_Input">
            <shadow type="text" id="vXgP*4a|N+iyrVq~a|1d">
              <field name="TEXT">screenVignette_1</field>
            </shadow>
          </value>
          <value name="screenVignette_Z_Index_Input">
            <shadow type="math_number" id="Nh/NlvnqezU8/Q6mzS9)">
              <field name="NUM">30</field>
            </shadow>
          </value>
          <value name="screenVignette_Radius_Input">
            <shadow type="text" id="gn)RO$Np,}^{N7=jdrZ/">
              <field name="TEXT">62%</field>
            </shadow>
          </value>
          <value name="screenVignette_Opacity_CENTER">
            <shadow type="math_number" id="-w]6EH-F|5C]fAGPcZLH">
              <field name="NUM">0</field>
            </shadow>
          </value>
          <value name="colorInput_1_OFFSET">
            <shadow type="math_number" id="_53D~rj.Oe%/[16n#DgV">
              <field name="NUM">0</field>
            </shadow>
          </value>
          <value name="screenVignette_Opacity_MID">
            <shadow type="math_number" id="hHgTZ$u_*VG@TFL{chj^">
              <field name="NUM">0</field>
            </shadow>
          </value>
          <value name="colorInput_2_OFFSET">
            <shadow type="math_number" id="A;8FWX}pVF_0=Rzol_`E">
              <field name="NUM">0.3</field>
            </shadow>
          </value>
          <value name="screenVignette_Opacity_OUTER">
            <shadow type="math_number" id="9FI_%)O-//$ORH8rYOuC">
              <field name="NUM">0.98</field>
            </shadow>
          </value>
          <value name="colorInput_3_OFFSET">
            <shadow type="math_number" id="=6g(FAJ7hhdd-)Otno.i">
              <field name="NUM">2</field>
            </shadow>
          </value>
        </block>
      </statement>
    </block>
  </tab>
  <editorsettings viewport-x="697.8" viewport-y="62" viewport-w="622.2" viewport-h="540" viewport-hidden="true" toolbox-library-mode="false" toolbox-minimized-mode="false"></editorsettings>
</xml>